odoo/addons/product_form_pricelist/README.rst
odoo/addons/product_form_pricelist/__init__.py
odoo/addons/product_form_pricelist/__manifest__.py
odoo/addons/product_form_pricelist/i18n/product_form_pricelist.pot
odoo/addons/product_form_pricelist/models/__init__.py
odoo/addons/product_form_pricelist/models/product_pricelist_item.py
odoo/addons/product_form_pricelist/models/product_template.py
odoo/addons/product_form_pricelist/models/res_config_settings.py
odoo/addons/product_form_pricelist/readme/CONFIGURATION.rst
odoo/addons/product_form_pricelist/readme/CONTRIBUTORS.rst
odoo/addons/product_form_pricelist/readme/DESCRIPTION.rst
odoo/addons/product_form_pricelist/readme/USAGE.rst
odoo/addons/product_form_pricelist/security/res_groups.xml
odoo/addons/product_form_pricelist/static/description/icon.png
odoo/addons/product_form_pricelist/static/description/index.html
odoo/addons/product_form_pricelist/tests/__init__.py
odoo/addons/product_form_pricelist/tests/test_pricelist.py
odoo/addons/product_form_pricelist/views/product_template_view.xml
odoo/addons/product_form_pricelist/views/product_view.xml
odoo/addons/product_form_pricelist/views/res_config_settings_view.xml
odoo14_addon_product_form_pricelist-14.0.1.0.1.dist-info/METADATA
odoo14_addon_product_form_pricelist-14.0.1.0.1.dist-info/WHEEL
odoo14_addon_product_form_pricelist-14.0.1.0.1.dist-info/top_level.txt
odoo14_addon_product_form_pricelist-14.0.1.0.1.dist-info/RECORD
